{
    "name": "bedroom-mark",

    "_path": {
        "media-root": "/mnt/md6-media",
        "music-metadata": "music/metadata"
    },
    "path": {
        "media-root": "/home/gnome",
        "music-metadata": ".cache"
    },

    "mopidy": {
        "_host": "media.home.whalebarn.com",
        "host": "localhost",
        "http_port": "6682",
        "mpd_port": "6602"
    },
    "airplay": {
        "port": "5102"
    },
    "mqtt": {
        "host": "localhost"
    },
    "snapcast": {
        "_host": "media.home.whalebarn.com",
        "host": "localhost",
        "opts": ""
    },

    "end": true
}
